{"rank": "30", "sound_name": "l.luly_bckupl.luly_bckupUGC Original", "ugc_count": "2K\n                                        \n\n                                            2,161", "growth": "+150\n                                            \n \n                                                    +9.62\n                                                    %", "author_country": "\ud83c\udde7\ud83c\udded\n BH", "tokchart_url": "https://tokchart.com/dashboard/tiktok-sound/7524504149237467935", "tiktok_direct_url": "https://www.tiktok.com/music/original-sound-lluly-bckup-7524504149237467935", "fetch_timestamp": "2025-12-05 00:11:55", "ingested_at": "2025-12-05T00:11:55.416617"}
{"rank": "30", "sound_name": "dialaabboudofficialDiala AbboudUGC Original", "ugc_count": "113\n                                        \n\n                                            113", "growth": "0\n                                            \n \n                                                    0.00\n                                                    %", "author_country": "\ud83c\uddfa\ud83c\udde6\n UA", "tokchart_url": "https://tokchart.com/dashboard/tiktok-sound/7567860836360080146", "tiktok_direct_url": "https://www.tiktok.com/music/original-sound-7567860836360080146", "fetch_timestamp": "2025-12-05 00:11:56", "ingested_at": "2025-12-05T00:11:56.694074"}
{"rank": "30", "sound_name": "qqkdl\u062f\u064f\u0648\u062f\u0650\u064a .UGC Contains Music", "ugc_count": "326\n                                        \n\n                                            326", "growth": "+2\n                                            \n \n                                                    +0.63\n                                                    %", "author_country": "\ud83c\uddea\ud83c\uddec\n EG", "tokchart_url": "https://tokchart.com/dashboard/tiktok-sound/7567900435223218952", "tiktok_direct_url": "https://www.tiktok.com/music/original-sound-7567900435223218952", "fetch_timestamp": "2025-12-05 00:11:58", "ingested_at": "2025-12-05T00:11:58.125881"}
{"rank": "30", "sound_name": "\u0627\u0644\u0635\u0648\u062a \u0627\u0644\u0623\u0635\u0644\u064aNOUR\ud83d\udc51MUSICUGC Contains Music", "ugc_count": "9K\n                                        \n\n                                            9,984", "growth": "+552\n                                            \n \n                                                    +7.10\n                                                    %", "author_country": "\ud83c\uddea\ud83c\uddec\n EG", "tokchart_url": "https://tokchart.com/dashboard/tiktok-sound/7567988006653578002", "tiktok_direct_url": "https://www.tiktok.com/music/alsot-alasly-7567988006653578002", "fetch_timestamp": "2025-12-05 00:11:59", "ingested_at": "2025-12-05T00:11:59.948374"}
{"rank": "30", "sound_name": "\u0627\u0644\u0635\u0648\u062a \u0627\u0644\u0623\u0635\u0644\u064asaltana_musicUGC Original", "ugc_count": "359\n                                        \n\n                                            359", "growth": "+4\n                                            \n \n                                                    +1.18\n                                                    %", "author_country": "\ud83c\uddea\ud83c\uddec\n EG", "tokchart_url": "https://tokchart.com/dashboard/tiktok-sound/7567994248592689928", "tiktok_direct_url": "https://www.tiktok.com/music/alsot-alasly-7567994248592689928", "fetch_timestamp": "2025-12-05 00:12:01", "ingested_at": "2025-12-05T00:12:01.177133"}
{"rank": "30", "sound_name": "\u0627\u0644\u0635\u0648\u062a \u0627\u0644\u0623\u0635\u0644\u064a\ufbbc\u0648\u0627\u062e\u062f\u060c\u0628\u0627\u0644\u0643\u060c\u0645\u0646\u060c\u0627\u0644\u062d\u062a\u0647\u060c\u062f\u064a\ud83e\uddcf\ud83c\udffb\u200d\u2642\ufe0fCommercial", "ugc_count": "5K\n                                        \n\n                                            5,780", "growth": "+76\n                                            \n \n                                                    +1.37\n                                                    %", "author_country": "\ud83c\uddea\ud83c\uddec\n EG", "tokchart_url": "https://tokchart.com/dashboard/tiktok-sound/7568083408476424967", "tiktok_direct_url": "https://www.tiktok.com/music/alsot-alasly-7568083408476424967", "fetch_timestamp": "2025-12-05 00:12:02", "ingested_at": "2025-12-05T00:12:02.824867"}
{"rank": "30", "sound_name": "\u0627\u0644\u0635\u0648\u062a \u0627\u0644\u0623\u0635\u0644\u064amayar_elsabahUGC Original", "ugc_count": "350\n                                        \n\n                                            350", "growth": "+2\n                                            \n \n                                                    +0.58\n                                                    %", "author_country": "\ud83c\uddea\ud83c\uddec\n EG", "tokchart_url": "https://tokchart.com/dashboard/tiktok-sound/7505549511394102032", "tiktok_direct_url": "https://www.tiktok.com/music/alsot-alasly-7505549511394102032", "fetch_timestamp": "2025-12-05 00:12:04", "ingested_at": "2025-12-05T00:12:04.088600"}
{"rank": "30", "sound_name": "\u0627\u0644\u0635\u0648\u062a \u0627\u0644\u0623\u0635\u0644\u064a\ud835\udc75\u0640\ud83d\udda4UGC Contains Music", "ugc_count": "5K\n                                        \n\n                                            5,981", "growth": "-1\n                                            \n \n                                                    -0.02\n                                                    %", "author_country": "\ud83c\uddea\ud83c\uddec\n EG", "tokchart_url": "https://tokchart.com/dashboard/tiktok-sound/7544018413015550736", "tiktok_direct_url": "https://www.tiktok.com/music/original-sound-nadamidoo769dodo-7544018413015550736", "fetch_timestamp": "2025-12-05 00:12:05", "ingested_at": "2025-12-05T00:12:05.622336"}
{"rank": "30", "sound_name": "Shadid El Gazibya _ \u0634\u062f\u064a\u062f \u0627\u0644\u062c\u0627\u0630\u0628\u064a\u0629Sherif MoatamedUGC Original", "ugc_count": "65\n                                        \n\n                                            65", "growth": "0\n                                            \n \n                                                    0.00\n                                                    %", "author_country": "\ud83c\uddea\ud83c\uddec\n EG", "tokchart_url": "https://tokchart.com/dashboard/tiktok-sound/7572287760355903505", "tiktok_direct_url": "https://www.tiktok.com/music/shadid-el-gazibya-shdyd-algathby-7572287760355903505", "fetch_timestamp": "2025-12-05 00:12:07", "ingested_at": "2025-12-05T00:12:07.027833"}
{"rank": "30", "sound_name": "\u0627\u0644\u0635\u0648\u062a \u0627\u0644\u0623\u0635\u0644\u064a\u0631\u064f\u0642\u0650\u0640\u0640\u064a\u0640\u0640\u0629\"UGC Original", "ugc_count": "6K\n                                        \n\n                                            6,136", "growth": "+497\n                                            \n \n                                                    +10.70\n                                                    %", "author_country": "\ud83c\uddea\ud83c\uddec\n EG", "tokchart_url": "https://tokchart.com/dashboard/tiktok-sound/7572305396317031176", "tiktok_direct_url": "https://www.tiktok.com/music/alsot-alasly-7572305396317031176", "fetch_timestamp": "2025-12-05 00:12:06", "ingested_at": "2025-12-05T00:12:06.490380"}